polony/__init__.py
polony/checkpoints/classifier_57_0.8896.pth
polony/checkpoints/test.pth
polony/checkpoints/unet_49_1.7496.pth
polony/config/config.yaml
polony/config/config_kaggle.yaml
polony/data/__init__.py
polony/data/make_dataset.py
polony/data/utils.py
polony/efficacy/__init__.py
polony/efficacy/polony_to_phage.py
polony/models/__init__.py
polony/models/models.py
polony/models/predict_model.py
polony/models/train_model.py
polony/models/utils.py
polony/run.py
polony-0.6.5.dist-info/LICENSE
polony-0.6.5.dist-info/METADATA
polony-0.6.5.dist-info/WHEEL
polony-0.6.5.dist-info/RECORD
