Metadata-Version: 2.1
Name: polony
Version: 0.6.5
Summary: 
Home-page: https://kirill-push.github.io/polony-counting/
License: MIT
Author: Kirill Pushkarev
Author-email: kirillpush@gmail.com
Requires-Python: >=3.9,<4.0
Classifier: License :: OSI Approved :: MIT License
Classifier: Programming Language :: Python :: 3
Classifier: Programming Language :: Python :: 3.9
Classifier: Programming Language :: Python :: 3.10
Classifier: Programming Language :: Python :: 3.11
Classifier: Programming Language :: Python :: 3.12
Requires-Dist: Pillow (>=10.1.0,<11.0.0)
Requires-Dist: gdown (>=4.7.1,<5.0.0)
Requires-Dist: h5py (>=3.9.0,<4.0.0)
Requires-Dist: matplotlib (>=3.7.0,<4.0.0)
Requires-Dist: opencv-python-headless (>=4.8.0,<5.0.0)
Requires-Dist: pandas (>=2.1.4,<3.0.0)
Requires-Dist: pyyaml (>=6.0.1,<7.0.0)
Requires-Dist: roifile (>=2023.5.12,<2024.0.0)
Requires-Dist: scikit-learn (>=1.2.2,<2.0.0)
Requires-Dist: tifffile (>=2023.8.12,<2024.0.0)
Requires-Dist: torch (==2.0.0+cu118)
Requires-Dist: torchvision (>=0.15.0,<0.16.0)
Requires-Dist: types-pyyaml (>=6.0.12.12,<7.0.0.0)
Requires-Dist: wandb (>=0.16.0,<0.17.0)
Project-URL: Repository, https://github.com/kirill-push/polony-counting
